CHANGES.txt
LICENSE.txt
MANIFEST.in
README.md
fastentrypoints.py
requirements.txt
setup.py
test_howdoi.py
howdoi/__init__.py
howdoi/__main__.py
howdoi/errors.py
howdoi/howdoi.py
howdoi.egg-info/PKG-INFO
howdoi.egg-info/SOURCES.txt
howdoi.egg-info/dependency_links.txt
howdoi.egg-info/entry_points.txt
howdoi.egg-info/requires.txt
howdoi.egg-info/top_level.txt