Metadata-Version: 2.1
Name: howdoi
Version: 2.0.18
Summary: Instant coding answers via the command line
Home-page: https://github.com/gleitz/howdoi
Author: Benjamin Gleitzman
Author-email: gleitz@mit.edu
Maintainer: Benjamin Gleitzman
Maintainer-email: gleitz@mit.edu
License: MIT
Keywords: howdoi help console command line answer
Platform: UNKNOWN
Classifier: Development Status :: 5 - Production/Stable
Classifier: Environment :: Console
Classifier: Intended Audience :: Developers
Classifier: Programming Language :: Python :: 3
Classifier: Programming Language :: Python :: 3.6
Classifier: Programming Language :: Python :: 3.7
Classifier: Programming Language :: Python :: 3.8
Classifier: Programming Language :: Python :: 3.9
Classifier: Topic :: Documentation
